[
    {
        "title": "Квартиры",
        "isIcon": true,
        "list": [
            {
                "_id": 0,
                "label": "Квартиры в Москве",
                "value": "Квартиры в Москве",
                "path": "/estates?typeId=63fa1ed26ac7a5d3db84a26d&cityId=63fa1ed66ac7a5d3db84a2df"
            },
            {
                "_id": 1,
                "label": "Квартиры в Санкт-Петербурге",
                "value": "Квартиры в Санкт-Петербурге",
                "path": "/estates?typeId=63fa1ed26ac7a5d3db84a26d&cityId=63fa1ed66ac7a5d3db84a2e0"
            },
            {
                "_id": 2,
                "label": "Квартиры в Екатеринбурге",
                "value": "Квартиры в Екатеринбурге",
                "path": "/estates?typeId=63fa1ed26ac7a5d3db84a26d&cityId=63fa1ed66ac7a5d3db84a2e3"
            },
            {
                "_id": 3,
                "label": "Квартиры в Омске",
                "value": "Квартиры в Омске",
                "path": "/estates?typeId=63fa1ed26ac7a5d3db84a26d&cityId=63fa1ed66ac7a5d3db84a2e1"
            },
            {
                "_id": 4,
                "label": "Квартиры в Красноярске",
                "value": "Квартиры в Красноярске",
                "path": "/estates?typeId=63fa1ed26ac7a5d3db84a26d&cityId=63fa1ed66ac7a5d3db84a2e2"
            },
            {
                "_id": 5,
                "label": "Квартиры в Воронеже",
                "value": "Квартиры в Воронеже",
                "path": "/estates?typeId=63fa1ed26ac7a5d3db84a26d&cityId=63fa1ed66ac7a5d3db84a2e4"
            }
        ]
    },
    {
        "title": "Коттеджи и усадьбы",
        "list": [
            {
                "_id": 0,
                "value": "Коттеджы и усадьбы в Москве",
                "label": "Коттеджы и усадьбы в Москве",
                "path": "/estates?typeId=63fa1ed26ac7a5d3db84a26e&cityId=63fa1ed66ac7a5d3db84a2df"
            },
            {
                "_id": 1,
                "label": "Коттеджы и усадьбы в Санкт-Петербурге",
                "value": "Коттеджы и усадьбы в Санкт-Петербурге",
                "path": "/estates?typeId=63fa1ed26ac7a5d3db84a26e&cityId=63fa1ed66ac7a5d3db84a2e0"
            },
            {
                "_id": 2,
                "label": "Коттеджы и усадьбы в Екатеринбурге",
                "value": "Коттеджы и усадьбы в Екатеринбурге",
                "path": "/estates?typeId=63fa1ed26ac7a5d3db84a26e&cityId=63fa1ed66ac7a5d3db84a2e3"
            },
            {
                "_id": 3,
                "label": "Коттеджы и усадьбы в Омске",
                "value": "Коттеджы и усадьбы в Омске",
                "path": "/estates?typeId=63fa1ed26ac7a5d3db84a26e&cityId=63fa1ed66ac7a5d3db84a2e1"
            },
            {
                "_id": 4,
                "label": "Коттеджы и усадьбы в Красноярске",
                "value": "Коттеджы и усадьбы в Красноярске",
                "path": "/estates?typeId=63fa1ed26ac7a5d3db84a26e&cityId=63fa1ed66ac7a5d3db84a2e2"
            },
            {
                "_id": 5,
                "label": "Коттеджы и усадьбы в Воронеже",
                "value": "Коттеджы и усадьбы в Воронеже",
                "path": "/estates?typeId=63fa1ed26ac7a5d3db84a26e&cityId=63fa1ed66ac7a5d3db84a2e4"
            }
        ]
    },
    {
        "title": "Бани и cауны",
        "list": [
            {
                "_id": 0,
                "value": "Бани и сауны в Москве",
                "label": "Бани и сауны в Москве",
                "path": "/estates?typeId=63fa1ed26ac7a5d3db84a26f&cityId=63fa1ed66ac7a5d3db84a2df"
            },
            {
                "_id": 1,
                "value": "Бани и сауны в Санкт-Петербурге",
                "label": "Бани и сауны в Санкт-Петербурге",
                "path": "/estates?typeId=63fa1ed26ac7a5d3db84a26f&cityId=63fa1ed66ac7a5d3db84a2e0"
            },
            {
                "_id": 2,
                "value": "Бани и сауны в Екатеринбурге",
                "label": "Бани и сауны в Екатеринбурге",
                "path": "/estates?typeId=63fa1ed26ac7a5d3db84a26f&cityId=63fa1ed66ac7a5d3db84a2e3"
            },
            {
                "_id": 3,
                "value": "Бани и сауны в Омске",
                "label": "Бани и сауны в Омске",
                "path": "/estates?typeId=63fa1ed26ac7a5d3db84a26f&cityId=63fa1ed66ac7a5d3db84a2e1"
            },
            {
                "_id": 4,
                "value": "Бани и сауны в Красноярске",
                "label": "Бани и сауны в Красноярске",
                "path": "/estates?typeId=63fa1ed26ac7a5d3db84a26f&cityId=63fa1ed66ac7a5d3db84a2e2"
            },
            {
                "_id": 5,
                "value": "Бани и сауны в Воронеже",
                "label": "Бани и сауны в Воронеже",
                "path": "/estates?typeId=63fa1ed26ac7a5d3db84a26f&cityId=63fa1ed66ac7a5d3db84a2e4"
            }
        ]
    },
    {
        "title": "Авто напрокат",
        "list": [
            {
                "_id": 0,
                "value": "Авто напрокат в Москве",
                "label": "Авто напрокат в Москве",
                "path": "/estates?typeId=63fa1ed26ac7a5d3db84a270&cityId=63fa1ed66ac7a5d3db84a2df"
            },
            {
                "_id": 1,
                "value": "Авто напрокат в Санкт-Петербурге",
                "label": "Авто напрокат в Санкт-Петербурге",
                "path": "/estates?typeId=63fa1ed26ac7a5d3db84a270&cityId=63fa1ed66ac7a5d3db84a2e0"
            },
            {
                "_id": 2,
                "value": "Авто напрокат в Екатеринбурге",
                "label": "Авто напрокат в Екатеринбурге",
                "path": "/estates?typeId=63fa1ed26ac7a5d3db84a270&cityId=63fa1ed66ac7a5d3db84a2e3"
            },
            {
                "_id": 3,
                "value": "Авто напрокат в Омске",
                "label": "Авто напрокат в Омске",
                "path": "/estates?typeId=63fa1ed26ac7a5d3db84a270&cityId=63fa1ed66ac7a5d3db84a2e1"
            },
            {
                "_id": 4,
                "value": "Авто напрокат в Красноярске",
                "label": "Авто напрокат в Красноярске",
                "path": "/estates?typeId=63fa1ed26ac7a5d3db84a270&cityId=63fa1ed66ac7a5d3db84a2e2"
            },
            {
                "_id": 5,
                "value": "Авто напрокат в Воронеже",
                "label": "Авто напрокат в Воронеже",
                "path": "/estates?typeId=63fa1ed26ac7a5d3db84a270&cityId=63fa1ed66ac7a5d3db84a2e4"
            }
        ]
    }
]
